fitter/__init__.py
fitter/fitter.py
fitter/histfit.py
fitter/main.py
fitter-1.7.0.dist-info/LICENSE
fitter-1.7.0.dist-info/METADATA
fitter-1.7.0.dist-info/WHEEL
fitter-1.7.0.dist-info/entry_points.txt
fitter-1.7.0.dist-info/RECORD
