Metadata-Version: 2.1
Name: fitter
Version: 1.7.0
Summary: A tool to fit data to many distributions and get the best one(s)
License: GPL
Keywords: fit,distribution,fitting,scipy
Author: Thomas Cokelaer
Author-email: cokelaer@gmail.com
Requires-Python: >=3.8,<4.0
Classifier: Development Status :: 5 - Production/Stable
Classifier: Intended Audience :: Developers
Classifier: Intended Audience :: Education
Classifier: Intended Audience :: End Users/Desktop
Classifier: Intended Audience :: Science/Research
Classifier: License :: OSI Approved :: GNU General Public License v3 (GPLv3)
Classifier: License :: Other/Proprietary License
Classifier: Operating System :: OS Independent
Classifier: Programming Language :: Python :: 3
Classifier: Programming Language :: Python :: 3.8
Classifier: Programming Language :: Python :: 3.9
Classifier: Programming Language :: Python :: 3.10
Classifier: Programming Language :: Python :: 3.11
Classifier: Programming Language :: Python :: 3.10
Classifier: Programming Language :: Python :: 3.11
Classifier: Programming Language :: Python :: 3.8
Classifier: Programming Language :: Python :: 3.9
Classifier: Topic :: Scientific/Engineering :: Bio-Informatics
Classifier: Topic :: Scientific/Engineering :: Information Analysis
Classifier: Topic :: Software Development :: Libraries :: Python Modules
Requires-Dist: click (>=8.1.6,<9.0.0)
Requires-Dist: joblib (>=1.3.1,<2.0.0)
Requires-Dist: loguru (>=0.7.2,<0.8.0)
Requires-Dist: matplotlib (>=3.7.2,<4.0.0)
Requires-Dist: numpy (>=1.20.0,<2.0.0)
Requires-Dist: pandas (>=0.23.4,<3.0.0)
Requires-Dist: rich-click (>=1.7.2,<2.0.0)
Requires-Dist: scipy (>=0.18.0,<2.0.0)
Requires-Dist: tqdm (>=4.65.1,<5.0.0)
